resilient_lib/__init__.py
resilient_lib/components/__init__.py
resilient_lib/components/function_metrics.py
resilient_lib/components/function_result.py
resilient_lib/components/html2markdown.py
resilient_lib/components/integration_errors.py
resilient_lib/components/oauth2_client_credentials_session.py
resilient_lib/components/poller_common.py
resilient_lib/components/requests_common.py
resilient_lib/components/resilient_common.py
resilient_lib/components/templates_common.py
resilient_lib/components/workflow_status.py
resilient_lib/ui/__init__.py
resilient_lib/ui/common.py
resilient_lib/ui/conditions.py
resilient_lib/ui/elements.py
resilient_lib/ui/tab.py
resilient_lib/util/__init__.py
resilient_lib/util/config.py
resilient_lib/util/constants.py
resilient_lib-51.0.7.2.16540.dist-info/METADATA
resilient_lib-51.0.7.2.16540.dist-info/WHEEL
resilient_lib-51.0.7.2.16540.dist-info/entry_points.txt
resilient_lib-51.0.7.2.16540.dist-info/top_level.txt
resilient_lib-51.0.7.2.16540.dist-info/RECORD
