Metadata-Version: 2.4
Name: resilient_lib
Version: 51.0.7.2.16540
Summary: Python module with library calls which facilitate the development of Apps for IBM SOAR
Home-page: https://github.com/ibmresilient/resilient-python-api/tree/main/resilient-lib
Author: IBM SOAR
License: MIT
Project-URL: Documentation, https://ibm.biz/soar-docs
Project-URL: API Docs, https://ibm.biz/soar-python-docs
Project-URL: IBM Community, https://ibm.biz/soarcommunity
Project-URL: Change Log, https://ibm.biz/resilient-lib-changes
Keywords: ibm,soar,resilient,resilient-circuits,circuits,resilient-lib,common
Classifier: Programming Language :: Python :: 3.9
Classifier: Programming Language :: Python :: 3.11
Classifier: Programming Language :: Python :: 3.12
Requires-Python: >=3.9
Requires-Dist: resilient>=51.0.7.2
Requires-Dist: pytz~=2024.1
Requires-Dist: deprecated~=1.2
Requires-Dist: beautifulsoup4~=4.9
Requires-Dist: jinja2~=3.1; python_version > "3.6"
Requires-Dist: retry2
